<?xml version="1.0" encoding="utf-16"?>
<MotifSite xmlns:xsd="http://www.w3.org/2001/XMLSchema" xmlns:xsi="http://www.w3.org/2001/XMLSchema-instance" logo="http://regprecise.lbl.gov/RegPrecise/logos/5425_large.png">
  <Family>ArsR</Family>
  <RegulationMode>repressor</RegulationMode>
  <BiologicalProcess>Heat shock response</BiologicalProcess>
  <Effector />
  <Regulog Key="Phr - Archaeoglobales" Value="http://regprecise.lbl.gov/RegPrecise/regulog.jsp?regulog_id=5425" />
  <Taxonomy Key="" Value="http://regprecise.lbl.gov/RegPrecise/" />
  <Sites>
    <FastaObject LocusTag="AF1971" Name="hsp20-2" Position="-56" Score="6">
      <Sequence>CTACCTAACATAAAGTTAGGTTA</Sequence>
      <Bacteria>Archaeoglobus fulgidus DSM 4304</Bacteria>
    </FastaObject>
    <FastaObject LocusTag="AF1298" Name="phr" Position="-34" Score="6.3">
      <Sequence>AAACCTAACATAAAGTTAGTAAC</Sequence>
      <Bacteria>Archaeoglobus fulgidus DSM 4304</Bacteria>
    </FastaObject>
    <FastaObject LocusTag="Arcpr_1089" Name="hsp20-2" Position="-48" Score="6.2">
      <Sequence>TTTACTAACTAAAGGTTAGTAGT</Sequence>
      <Bacteria>Archaeoglobus profundus DSM 5631</Bacteria>
    </FastaObject>
    <FastaObject LocusTag="Arcpr_0812" Name="phr" Position="-43" Score="6.5">
      <Sequence>TTTACTAACCAAAAGTTAGTAAA</Sequence>
      <Bacteria>Archaeoglobus profundus DSM 5631</Bacteria>
    </FastaObject>
    <FastaObject LocusTag="Ferp_0363" Name="hsp20-2" Position="-46" Score="6.6">
      <Sequence>AATCCTAACTTAAAGTTAGGATT</Sequence>
      <Bacteria>Ferroglobus placidus DSM 10642</Bacteria>
    </FastaObject>
    <FastaObject LocusTag="Ferp_0217" Name="phr" Position="-58" Score="6.3">
      <Sequence>TTTACTAACACAAAGTTAGTAAC</Sequence>
      <Bacteria>Ferroglobus placidus DSM 10642</Bacteria>
    </FastaObject>
  </Sites>
</MotifSite>