<?xml version="1.0" encoding="utf-16"?>
<MotifSite xmlns:xsd="http://www.w3.org/2001/XMLSchema" xmlns:xsi="http://www.w3.org/2001/XMLSchema-instance" logo="http://regprecise.lbl.gov/RegPrecise/logos/5931_large.png">
  <Family>BirA</Family>
  <RegulationMode>repressor</RegulationMode>
  <BiologicalProcess>Biotin biosynthesis</BiologicalProcess>
  <Effector>Biotin</Effector>
  <Regulog Key="BirA - Deinococcus-Thermus" Value="http://regprecise.lbl.gov/RegPrecise/regulog.jsp?regulog_id=5931" />
  <Taxonomy Key="Deinococcus-Thermus" Value="http://regprecise.lbl.gov/RegPrecise/collection_tax.jsp?collection_id=159" />
  <Sites>
    <FastaObject LocusTag="TaqDRAFT_5371" Name="bioY" Position="-61" Score="9.4">
      <Sequence>CCGTCAACC---------------GGTTGACGA</Sequence>
      <Bacteria>Thermus aquaticus Y51MC23</Bacteria>
    </FastaObject>
    <FastaObject LocusTag="TTC0242" Name="bioB" Position="-35" Score="9.2">
      <Sequence>TCGTAAACT---------------GGTTTACGA</Sequence>
      <Bacteria>Thermus thermophilus HB27</Bacteria>
    </FastaObject>
    <FastaObject LocusTag="TTC0548" Name="bioY" Position="-97" Score="9.4">
      <Sequence>ACGTCAACC---------------GGTTGACGA</Sequence>
      <Bacteria>Thermus thermophilus HB27</Bacteria>
    </FastaObject>
  </Sites>
</MotifSite>