<?xml version="1.0" encoding="utf-16"?>
<MotifSite xmlns:xsd="http://www.w3.org/2001/XMLSchema" xmlns:xsi="http://www.w3.org/2001/XMLSchema-instance" logo="http://regprecise.lbl.gov/RegPrecise/logos/2275_large.png">
  <Family>LacI</Family>
  <RegulationMode>repressor</RegulationMode>
  <BiologicalProcess>Ribose utilization</BiologicalProcess>
  <Effector>Ribose</Effector>
  <Regulog Key="RbsR - Vibrionales" Value="http://regprecise.lbl.gov/RegPrecise/regulog.jsp?regulog_id=2275" />
  <Taxonomy Key="Vibrionales" Value="http://regprecise.lbl.gov/RegPrecise/collection_tax.jsp?collection_id=105" />
  <Sites>
    <FastaObject LocusTag="VCA0127" Name="rbsD" Position="-86" Score="7">
      <Sequence>TCATCGAAACGTTTCGATGT</Sequence>
      <Bacteria>Vibrio cholerae O1 biovar eltor str. N16961</Bacteria>
    </FastaObject>
    <FastaObject LocusTag="VV20061" Name="rbsD" Position="-72" Score="7.2">
      <Sequence>TCATCGAAACGTTTCGATGA</Sequence>
      <Bacteria>Vibrio vulnificus CMCP6</Bacteria>
    </FastaObject>
    <FastaObject LocusTag="VIBHAR_06146" Name="rbsD" Position="-222" Score="6.2">
      <Sequence>CTATCGAAACGTTTCGATTT</Sequence>
      <Bacteria>Vibrio harveyi ATCC BAA-1116</Bacteria>
    </FastaObject>
    <FastaObject LocusTag="VIBHAR_06146" Name="rbsD" Position="-95" Score="7">
      <Sequence>TCATCGAAACGTTTCGATGT</Sequence>
      <Bacteria>Vibrio harveyi ATCC BAA-1116</Bacteria>
    </FastaObject>
    <FastaObject LocusTag="VPA1087" Name="rbsD" Position="-226" Score="7">
      <Sequence>CCATCGAAACGTTTCGATGA</Sequence>
      <Bacteria>Vibrio parahaemolyticus RIMD 2210633</Bacteria>
    </FastaObject>
    <FastaObject LocusTag="VPA1087" Name="rbsD" Position="-96" Score="6.7">
      <Sequence>GCATCGAAACGTTTCGATGA</Sequence>
      <Bacteria>Vibrio parahaemolyticus RIMD 2210633</Bacteria>
    </FastaObject>
    <FastaObject LocusTag="VSAK1_16182" Name="rbsD" Position="-170" Score="6.6">
      <Sequence>TCATCGAAACGTTTCGATAG</Sequence>
      <Bacteria>Vibrio shilonii AK1</Bacteria>
    </FastaObject>
    <FastaObject LocusTag="VSAK1_16182" Name="rbsD" Position="-87" Score="7.2">
      <Sequence>TCATCGAAACGTTTCGATGA</Sequence>
      <Bacteria>Vibrio shilonii AK1</Bacteria>
    </FastaObject>
    <FastaObject LocusTag="VS_II0940" Name="rbsD" Position="-26" Score="6.6">
      <Sequence>CTATCGAAACGTTTCGATGG</Sequence>
      <Bacteria>Vibrio splendidus LGP32</Bacteria>
    </FastaObject>
    <FastaObject LocusTag="VS_II0940" Name="rbsD" Position="-104" Score="7">
      <Sequence>CCATCGAAACGTTTCGATGA</Sequence>
      <Bacteria>Vibrio splendidus LGP32</Bacteria>
    </FastaObject>
    <FastaObject LocusTag="VF_1444" Name="rbsD" Position="-71" Score="6.4">
      <Sequence>TTACGCAAACGTTTCGATGA</Sequence>
      <Bacteria>Vibrio fischeri ES114</Bacteria>
    </FastaObject>
    <FastaObject LocusTag="VSAL_I1372" Name="rbsD" Position="-70" Score="6.4">
      <Sequence>TTACGCAAACGTTTCGATGA</Sequence>
      <Bacteria>Vibrio salmonicida LFI1238</Bacteria>
    </FastaObject>
    <FastaObject LocusTag="VAS14_09005" Name="rbsD" Position="-226" Score="6.8">
      <Sequence>TTATCGAAACGTTTCGATGG</Sequence>
      <Bacteria>Vibrio angustum S14</Bacteria>
    </FastaObject>
    <FastaObject LocusTag="VAS14_09005" Name="rbsD" Position="-96" Score="6.6">
      <Sequence>CTATCGAAACGTTTCGATGG</Sequence>
      <Bacteria>Vibrio angustum S14</Bacteria>
    </FastaObject>
    <FastaObject LocusTag="PBPRB1556" Name="rbsD" Position="-118" Score="5.7">
      <Sequence>CCATCGAAACGTTTGCGTAA</Sequence>
      <Bacteria>Photobacterium profundum SS9</Bacteria>
    </FastaObject>
  </Sites>
</MotifSite>