<?xml version="1.0" encoding="utf-16"?>
<MotifSite xmlns:xsd="http://www.w3.org/2001/XMLSchema" xmlns:xsi="http://www.w3.org/2001/XMLSchema-instance" logo="http://regprecise.lbl.gov/RegPrecise/logos/6295_large.png">
  <Family>GntR/MocR</Family>
  <RegulationMode />
  <BiologicalProcess>Pyridoxine/pyridoxal homeostasis</BiologicalProcess>
  <Effector>Pyridoxal-5-phosphate</Effector>
  <Regulog Key="PdxQ - Desulfuromonadales" Value="http://regprecise.lbl.gov/RegPrecise/regulog.jsp?regulog_id=6295" />
  <Taxonomy Key="Desulfuromonadales" Value="http://regprecise.lbl.gov/RegPrecise/collection_tax.jsp?collection_id=122" />
  <Sites>
    <FastaObject LocusTag="Dace_1192" Name="pdxO" Position="-123" Score="8.3">
      <Sequence>TTGTCC-(18)-CTGGCA-(10)-TGATAA</Sequence>
      <Bacteria>Desulfuromonas acetoxidans DSM 684</Bacteria>
    </FastaObject>
  </Sites>
</MotifSite>