<?xml version="1.0" encoding="utf-16"?>
<MotifSite xmlns:xsd="http://www.w3.org/2001/XMLSchema" xmlns:xsi="http://www.w3.org/2001/XMLSchema-instance" logo="http://regprecise.lbl.gov/RegPrecise/logos/1726_large.png">
  <Family>FUR</Family>
  <RegulationMode>repressor</RegulationMode>
  <BiologicalProcess>Zinc homeostasis</BiologicalProcess>
  <Effector>Zinc ion, (Zn2+)</Effector>
  <Regulog Key="Zur - Oceanospirillales/Alteromonadales" Value="http://regprecise.lbl.gov/RegPrecise/regulog.jsp?regulog_id=1726" />
  <Taxonomy Key="Oceanospirillales/Alteromonadales" Value="http://regprecise.lbl.gov/RegPrecise/collection_tax.jsp?collection_id=109" />
  <Sites>
    <FastaObject LocusTag="HCH_00656" Name="zbp" Position="-70" Score="5.7">
      <Sequence>GTTTCGTTATGTTATAACATAAA</Sequence>
      <Bacteria>Hahella chejuensis KCTC 2396</Bacteria>
    </FastaObject>
    <FastaObject LocusTag="HCH_02800" Name="yciC" Position="-59" Score="6.2">
      <Sequence>GTTTTGTTATGTTATAACATTTT</Sequence>
      <Bacteria>Hahella chejuensis KCTC 2396</Bacteria>
    </FastaObject>
    <FastaObject LocusTag="HCH_02942" Name="znuA" Position="-84" Score="6.3">
      <Sequence>GATATGTTACATCATAACATTTT</Sequence>
      <Bacteria>Hahella chejuensis KCTC 2396</Bacteria>
    </FastaObject>
    <FastaObject LocusTag="HCH_02413" Name="znuA" Position="-64" Score="6.3">
      <Sequence>ATAATGTTATGTTATAACCTTTC</Sequence>
      <Bacteria>Hahella chejuensis KCTC 2396</Bacteria>
    </FastaObject>
    <FastaObject LocusTag="HCH_00537" Name="zur" Position="-80" Score="5.3">
      <Sequence>CAATTGTTATAACATTACACTTC</Sequence>
      <Bacteria>Hahella chejuensis KCTC 2396</Bacteria>
    </FastaObject>
    <FastaObject LocusTag="HCH_02943" Name="" Position="-66" Score="4.9">
      <Sequence>AAAAAGATATGATGCAACATATC</Sequence>
      <Bacteria>Hahella chejuensis KCTC 2396</Bacteria>
    </FastaObject>
    <FastaObject LocusTag="HCH_01703" Name="zur2" Position="-211" Score="5.7">
      <Sequence>AAAAAGATATGATATAACGTATC</Sequence>
      <Bacteria>Hahella chejuensis KCTC 2396</Bacteria>
    </FastaObject>
    <FastaObject LocusTag="HCH_01703" Name="zur2" Position="-206" Score="5.2">
      <Sequence>GATATGATATAACGTATCTTTAT</Sequence>
      <Bacteria>Hahella chejuensis KCTC 2396</Bacteria>
    </FastaObject>
    <FastaObject LocusTag="Maqu_3429" Name="zbp" Position="-39" Score="5.6">
      <Sequence>AAAATGTTATAACATATCAAATA</Sequence>
      <Bacteria>Marinobacter aqueolei</Bacteria>
    </FastaObject>
    <FastaObject LocusTag="Maqu_1892" Name="znuA" Position="-48" Score="6.3">
      <Sequence>ATATTGTTATATTATAACGTTTC</Sequence>
      <Bacteria>Marinobacter aqueolei</Bacteria>
    </FastaObject>
    <FastaObject LocusTag="MELB17_02870" Name="zbp" Position="-34" Score="5.9">
      <Sequence>AAGATGTTATAACATAACTTTAC</Sequence>
      <Bacteria>Marinobacter sp. ELB17</Bacteria>
    </FastaObject>
    <FastaObject LocusTag="MELB17_08596" Name="znuA" Position="-68" Score="5.8">
      <Sequence>GTTATGTAATATTATAACATTCT</Sequence>
      <Bacteria>Marinobacter sp. ELB17</Bacteria>
    </FastaObject>
    <FastaObject LocusTag="MELB17_12891" Name="znuA" Position="-60" Score="5.7">
      <Sequence>GCAATGTTATAACATAACGTTCA</Sequence>
      <Bacteria>Marinobacter sp. ELB17</Bacteria>
    </FastaObject>
    <FastaObject LocusTag="MELB17_12886" Name="znuC" Position="-102" Score="5.5">
      <Sequence>TGAACGTTATGTTATAACATTGC</Sequence>
      <Bacteria>Marinobacter sp. ELB17</Bacteria>
    </FastaObject>
    <FastaObject LocusTag="RED65_11939" Name="PF08856" Position="-47" Score="5">
      <Sequence>GATATAATATATCATATCTTTTA</Sequence>
      <Bacteria>Oceanobacter sp. RED65</Bacteria>
    </FastaObject>
    <FastaObject LocusTag="RED65_11939" Name="PF08856" Position="-52" Score="5.4">
      <Sequence>CAAAAGATATAATATATCATATC</Sequence>
      <Bacteria>Oceanobacter sp. RED65</Bacteria>
    </FastaObject>
    <FastaObject LocusTag="MED92_15318" Name="zbp" Position="-28" Score="5.7">
      <Sequence>TTGTTGTTATATTATAACTTTTA</Sequence>
      <Bacteria>Oceanospirillum sp. MED92</Bacteria>
    </FastaObject>
    <FastaObject LocusTag="MED92_08311" Name="PF08856" Position="-44" Score="5.7">
      <Sequence>GTTATGTTATATTGTATCTTTTT</Sequence>
      <Bacteria>Oceanospirillum sp. MED92</Bacteria>
    </FastaObject>
    <FastaObject LocusTag="MED92_05848" Name="znuA" Position="-38" Score="5.7">
      <Sequence>TTTGTGTTATATTGTAACTTTAA</Sequence>
      <Bacteria>Oceanospirillum sp. MED92</Bacteria>
    </FastaObject>
    <FastaObject LocusTag="MED92_05843" Name="zur" Position="-43" Score="5.6">
      <Sequence>TTAAAGTTACAATATAACACAAA</Sequence>
      <Bacteria>Oceanospirillum sp. MED92</Bacteria>
    </FastaObject>
    <FastaObject LocusTag="MED92_02998" Name="" Position="-35" Score="5.9">
      <Sequence>ATATTGTTATGGTATAACATTTA</Sequence>
      <Bacteria>Oceanospirillum sp. MED92</Bacteria>
    </FastaObject>
    <FastaObject LocusTag="MED92_02998" Name="" Position="-138" Score="5.3">
      <Sequence>GCAATGTTATAATATAGCAATTA</Sequence>
      <Bacteria>Oceanospirillum sp. MED92</Bacteria>
    </FastaObject>
    <FastaObject LocusTag="MED92_08311" Name="PF08856" Position="-49" Score="5.1">
      <Sequence>TTAAAGTTATGTTATATTGTATC</Sequence>
      <Bacteria>Oceanospirillum sp. MED92</Bacteria>
    </FastaObject>
    <FastaObject LocusTag="MED92_02993" Name="pyrC2" Position="-152" Score="5.7">
      <Sequence>TAAATGTTATACCATAACAATAT</Sequence>
      <Bacteria>Oceanospirillum sp. MED92</Bacteria>
    </FastaObject>
    <FastaObject LocusTag="MED92_02993" Name="pyrC2" Position="-49" Score="5.5">
      <Sequence>TAATTGCTATATTATAACATTGC</Sequence>
      <Bacteria>Oceanospirillum sp. MED92</Bacteria>
    </FastaObject>
    <FastaObject LocusTag="Mmwyl1_1446" Name="yciC" Position="-39" Score="6.6">
      <Sequence>GAAATGTTATATCATAACATTTT</Sequence>
      <Bacteria>Marinomonas sp. MWYL1</Bacteria>
    </FastaObject>
    <FastaObject LocusTag="Mmwyl1_0929" Name="PF08856" Position="-18" Score="5.8">
      <Sequence>AAAATGTTATAACGTAACATGTT</Sequence>
      <Bacteria>Marinomonas sp. MWYL1</Bacteria>
    </FastaObject>
    <FastaObject LocusTag="Mmwyl1_0929" Name="PF08856" Position="-23" Score="4.6">
      <Sequence>TTTGTAAAATGTTATAACGTAAC</Sequence>
      <Bacteria>Marinomonas sp. MWYL1</Bacteria>
    </FastaObject>
    <FastaObject LocusTag="Mmwyl1_0291" Name="" Position="-51" Score="5.2">
      <Sequence>TACTTGTTATATCATAACAAAAT</Sequence>
      <Bacteria>Marinomonas sp. MWYL1</Bacteria>
    </FastaObject>
    <FastaObject LocusTag="Mmwyl1_1122" Name="" Position="-40" Score="5.9">
      <Sequence>GTATTGTTACGTTATAACATTAA</Sequence>
      <Bacteria>Marinomonas sp. MWYL1</Bacteria>
    </FastaObject>
    <FastaObject LocusTag="Sde_0060" Name="znuA" Position="-80" Score="6">
      <Sequence>GTTATGTTATCATATAACACTTT</Sequence>
      <Bacteria>Saccharophagus degradans 2-40</Bacteria>
    </FastaObject>
    <FastaObject LocusTag="Sde_0059" Name="zur" Position="-51" Score="6.1">
      <Sequence>AAAGTGTTATATGATAACATAAC</Sequence>
      <Bacteria>Saccharophagus degradans 2-40</Bacteria>
    </FastaObject>
    <FastaObject LocusTag="Sde_1980" Name="yciC" Position="-184" Score="5.6">
      <Sequence>ATAATGATATCATATATCATATC</Sequence>
      <Bacteria>Saccharophagus degradans 2-40</Bacteria>
    </FastaObject>
    <FastaObject LocusTag="TERTU_2263" Name="yciC" Position="-119" Score="5.5">
      <Sequence>ATAATGATATGGTATATCATAAC</Sequence>
      <Bacteria>Teredinibacter turnerae T7901</Bacteria>
    </FastaObject>
    <FastaObject LocusTag="TERTU_0054" Name="znuA" Position="-67" Score="6.1">
      <Sequence>GTTATGTTATCATATAACGTTTA</Sequence>
      <Bacteria>Teredinibacter turnerae T7901</Bacteria>
    </FastaObject>
    <FastaObject LocusTag="TERTU_0053" Name="zur" Position="-51" Score="6">
      <Sequence>TAAACGTTATATGATAACATAAC</Sequence>
      <Bacteria>Teredinibacter turnerae T7901</Bacteria>
    </FastaObject>
    <FastaObject LocusTag="TERTU_2263" Name="yciC" Position="-114" Score="6">
      <Sequence>GATATGGTATATCATAACGTTAC</Sequence>
      <Bacteria>Teredinibacter turnerae T7901</Bacteria>
    </FastaObject>
    <FastaObject LocusTag="CJA_3465" Name="yciC" Position="-46" Score="6.1">
      <Sequence>AATGTGTTATGTTATAACATATT</Sequence>
      <Bacteria>Cellvibrio japonicus Ueda107</Bacteria>
    </FastaObject>
    <FastaObject LocusTag="CJA_3480" Name="znuA" Position="-3" Score="5.4">
      <Sequence>GTTATGTTACTCTATAACCTTTC</Sequence>
      <Bacteria>Cellvibrio japonicus Ueda107</Bacteria>
    </FastaObject>
    <FastaObject LocusTag="CJA_3482" Name="zur" Position="-53" Score="5.3">
      <Sequence>GAAAGGTTATAGAGTAACATAAC</Sequence>
      <Bacteria>Cellvibrio japonicus Ueda107</Bacteria>
    </FastaObject>
    <FastaObject LocusTag="Csal_0192" Name="yciC" Position="-90" Score="5.9">
      <Sequence>AGAATGTTATGGTATAACATATC</Sequence>
      <Bacteria>Chromohalobacter salexigens DSM 3043</Bacteria>
    </FastaObject>
    <FastaObject LocusTag="Csal_0187" Name="zinT" Position="-70" Score="5.3">
      <Sequence>AGAAAGATATGTTATAACGTATT</Sequence>
      <Bacteria>Chromohalobacter salexigens DSM 3043</Bacteria>
    </FastaObject>
    <FastaObject LocusTag="Csal_0188" Name="znuA" Position="-63" Score="5.9">
      <Sequence>TATATGTTATAACATAACTCTTT</Sequence>
      <Bacteria>Chromohalobacter salexigens DSM 3043</Bacteria>
    </FastaObject>
    <FastaObject LocusTag="Csal_0189" Name="znuC" Position="-56" Score="5.9">
      <Sequence>AAAGAGTTATGTTATAACATATA</Sequence>
      <Bacteria>Chromohalobacter salexigens DSM 3043</Bacteria>
    </FastaObject>
    <FastaObject LocusTag="MED297_11280" Name="znuA" Position="-61" Score="5.6">
      <Sequence>GTTATGATACATCATATCATTTA</Sequence>
      <Bacteria>Reinekea sp. MED297</Bacteria>
    </FastaObject>
    <FastaObject LocusTag="MED297_11285" Name="znuC" Position="-124" Score="5.4">
      <Sequence>TAAATGATATGATGTATCATAAC</Sequence>
      <Bacteria>Reinekea sp. MED297</Bacteria>
    </FastaObject>
    <FastaObject LocusTag="MED297_11285" Name="znuC" Position="-119" Score="5.2">
      <Sequence>GATATGATGTATCATAACAAATA</Sequence>
      <Bacteria>Reinekea sp. MED297</Bacteria>
    </FastaObject>
    <FastaObject LocusTag="MED297_00400" Name="zur2" Position="-77" Score="5.9">
      <Sequence>TTAATGATATATCATATCATTTA</Sequence>
      <Bacteria>Reinekea sp. MED297</Bacteria>
    </FastaObject>
    <FastaObject LocusTag="ABO_1680" Name="dksA2" Position="-34" Score="5.7">
      <Sequence>GCAATGTTATAACATAACATGAA</Sequence>
      <Bacteria>Alcanivorax borkumensis SK2</Bacteria>
    </FastaObject>
    <FastaObject LocusTag="ABO_1681" Name="" Position="-51" Score="4.9">
      <Sequence>GTTATGTTATAACATTGCATCAA</Sequence>
      <Bacteria>Alcanivorax borkumensis SK2</Bacteria>
    </FastaObject>
    <FastaObject LocusTag="ABO_1681" Name="" Position="-56" Score="5.7">
      <Sequence>TTCATGTTATGTTATAACATTGC</Sequence>
      <Bacteria>Alcanivorax borkumensis SK2</Bacteria>
    </FastaObject>
  </Sites>
</MotifSite>