<?xml version="1.0" encoding="utf-16"?>
<MotifSite xmlns:xsd="http://www.w3.org/2001/XMLSchema" xmlns:xsi="http://www.w3.org/2001/XMLSchema-instance" logo="http://regprecise.lbl.gov/RegPrecise/logos/6299_large.png">
  <Family>GntR/MocR</Family>
  <RegulationMode />
  <BiologicalProcess />
  <Effector />
  <Regulog Key="CD3353 - Clostridia-2" Value="http://regprecise.lbl.gov/RegPrecise/regulog.jsp?regulog_id=6299" />
  <Taxonomy Key="Clostridia-2" Value="http://regprecise.lbl.gov/RegPrecise/collection_tax.jsp?collection_id=161" />
  <Sites>
    <FastaObject LocusTag="CD3354" Name="COG3382" Position="-102" Score="11.9">
      <Sequence>AAAAGTGGTTC-(14)-AAAAATGGAAC-(6)-ATCCACTTTTA</Sequence>
      <Bacteria>Clostridium difficile 630</Bacteria>
    </FastaObject>
  </Sites>
</MotifSite>