<?xml version="1.0" encoding="utf-16"?>
<MotifSite xmlns:xsd="http://www.w3.org/2001/XMLSchema" xmlns:xsi="http://www.w3.org/2001/XMLSchema-instance" logo="http://regprecise.lbl.gov/RegPrecise/logos/4791_large.png">
  <Family>Rex</Family>
  <RegulationMode>repressor</RegulationMode>
  <BiologicalProcess>Energy metabolism</BiologicalProcess>
  <Effector>NADH</Effector>
  <Regulog Key="Rex - Clostridia-2" Value="http://regprecise.lbl.gov/RegPrecise/regulog.jsp?regulog_id=4791" />
  <Taxonomy Key="Clostridia-2" Value="http://regprecise.lbl.gov/RegPrecise/collection_tax.jsp?collection_id=161" />
  <Sites>
    <FastaObject LocusTag="CLOBAR_02221" Name="CD2707" Position="-91" Score="4.9">
      <Sequence>ACGTTAAGAATTTAACAA</Sequence>
      <Bacteria>Clostridium bartlettii DSM 16795</Bacteria>
    </FastaObject>
    <FastaObject LocusTag="CLOBAR_01995" Name="lldD" Position="-94" Score="5.5">
      <Sequence>ATGTTAAAAAAATAACAT</Sequence>
      <Bacteria>Clostridium bartlettii DSM 16795</Bacteria>
    </FastaObject>
    <FastaObject LocusTag="CLOBAR_02282" Name="glcA" Position="-119" Score="5.2">
      <Sequence>ATGTTAATAAATAAACAA</Sequence>
      <Bacteria>Clostridium bartlettii DSM 16795</Bacteria>
    </FastaObject>
    <FastaObject LocusTag="CLOBAR_00255" Name="hydC" Position="-128" Score="4.7">
      <Sequence>TAGATAATTAAATAAAAA</Sequence>
      <Bacteria>Clostridium bartlettii DSM 16795</Bacteria>
    </FastaObject>
    <FastaObject LocusTag="CLOBAR_02282" Name="glcA" Position="-138" Score="4.3">
      <Sequence>TTTTTATTAATTTAAAAT</Sequence>
      <Bacteria>Clostridium bartlettii DSM 16795</Bacteria>
    </FastaObject>
    <FastaObject LocusTag="CLOBAR_00531" Name="nadA" Position="-113" Score="4.7">
      <Sequence>AAATTAAAAATTTAACTA</Sequence>
      <Bacteria>Clostridium bartlettii DSM 16795</Bacteria>
    </FastaObject>
    <FastaObject LocusTag="CLOBAR_00902" Name="hydC" Position="-125" Score="4.4">
      <Sequence>TATTTAAATTTTTAAAAA</Sequence>
      <Bacteria>Clostridium bartlettii DSM 16795</Bacteria>
    </FastaObject>
    <FastaObject LocusTag="CLOBAR_00502" Name="adhE" Position="-130" Score="5.3">
      <Sequence>ATGTTAAACAAATAACAA</Sequence>
      <Bacteria>Clostridium bartlettii DSM 16795</Bacteria>
    </FastaObject>
    <FastaObject LocusTag="CLOBAR_00502" Name="adhE" Position="-106" Score="4.8">
      <Sequence>AGGTTAATAATATAACAT</Sequence>
      <Bacteria>Clostridium bartlettii DSM 16795</Bacteria>
    </FastaObject>
    <FastaObject LocusTag="CLOBAR_00902" Name="hydC" Position="-169" Score="4.9">
      <Sequence>ATGTTAAAAAAGTATCAT</Sequence>
      <Bacteria>Clostridium bartlettii DSM 16795</Bacteria>
    </FastaObject>
    <FastaObject LocusTag="CLOBAR_00502" Name="adhE" Position="-188" Score="5.5">
      <Sequence>ATGATAAAAAAATAACAA</Sequence>
      <Bacteria>Clostridium bartlettii DSM 16795</Bacteria>
    </FastaObject>
    <FastaObject LocusTag="CLOBAR_01830" Name="rex" Position="-156" Score="4.3">
      <Sequence>ATAATATATTATTAACTA</Sequence>
      <Bacteria>Clostridium bartlettii DSM 16795</Bacteria>
    </FastaObject>
    <FastaObject LocusTag="CLOBAR_00711" Name="rex" Position="-37" Score="4">
      <Sequence>TTGTTATGAAAATATTAA</Sequence>
      <Bacteria>Clostridium bartlettii DSM 16795</Bacteria>
    </FastaObject>
    <FastaObject LocusTag="CLOBAR_00711" Name="rex" Position="-99" Score="4.1">
      <Sequence>TTGGTATAATATAATCAA</Sequence>
      <Bacteria>Clostridium bartlettii DSM 16795</Bacteria>
    </FastaObject>
    <FastaObject LocusTag="CD2354" Name="grdE" Position="-264" Score="5.5">
      <Sequence>TTGATAAATTATTAACAT</Sequence>
      <Bacteria>Clostridium difficile 630</Bacteria>
    </FastaObject>
    <FastaObject LocusTag="CD2354" Name="grdE" Position="-187" Score="4.5">
      <Sequence>TTGTTAAAAAAATAATTT</Sequence>
      <Bacteria>Clostridium difficile 630</Bacteria>
    </FastaObject>
    <FastaObject LocusTag="CD2707" Name="CD2707" Position="-34" Score="5.7">
      <Sequence>ATGTTAATAAATTAACAA</Sequence>
      <Bacteria>Clostridium difficile 630</Bacteria>
    </FastaObject>
    <FastaObject LocusTag="CD2540" Name="noxE" Position="-112" Score="5.2">
      <Sequence>ATGTTAAATAAATAACTA</Sequence>
      <Bacteria>Clostridium difficile 630</Bacteria>
    </FastaObject>
    <FastaObject LocusTag="CD1170" Name="PF09861" Position="-113" Score="4">
      <Sequence>TTGTTATAAAATAAATTA</Sequence>
      <Bacteria>Clostridium difficile 630</Bacteria>
    </FastaObject>
    <FastaObject LocusTag="CD1054" Name="bcd2" Position="-193" Score="5">
      <Sequence>TTGATTTTAAATTAACAA</Sequence>
      <Bacteria>Clostridium difficile 630</Bacteria>
    </FastaObject>
    <FastaObject LocusTag="CD1623" Name="fprA" Position="-63" Score="5.4">
      <Sequence>TTGTTTAAAATATAACAA</Sequence>
      <Bacteria>Clostridium difficile 630</Bacteria>
    </FastaObject>
    <FastaObject LocusTag="CD2344" Name="CD2344" Position="-190" Score="4.6">
      <Sequence>TTGTTAATTAAATCATAA</Sequence>
      <Bacteria>Clostridium difficile 630</Bacteria>
    </FastaObject>
    <FastaObject LocusTag="CD2344" Name="CD2344" Position="-129" Score="5.4">
      <Sequence>ATGTTAATTTAATAACAA</Sequence>
      <Bacteria>Clostridium difficile 630</Bacteria>
    </FastaObject>
    <FastaObject LocusTag="CD2344" Name="CD2344" Position="-66" Score="5.2">
      <Sequence>TTGTTAATTTAATAACGA</Sequence>
      <Bacteria>Clostridium difficile 630</Bacteria>
    </FastaObject>
    <FastaObject LocusTag="CD2966" Name="adhE" Position="-146" Score="5.1">
      <Sequence>ATGTTAAAAAAATAACTT</Sequence>
      <Bacteria>Clostridium difficile 630</Bacteria>
    </FastaObject>
    <FastaObject LocusTag="CD2966" Name="adhE" Position="-103" Score="5.6">
      <Sequence>ATGTTAATAAATTAACAT</Sequence>
      <Bacteria>Clostridium difficile 630</Bacteria>
    </FastaObject>
    <FastaObject LocusTag="CD0171" Name="rex" Position="-96" Score="4.6">
      <Sequence>TTGATATAATATAATCAA</Sequence>
      <Bacteria>Clostridium difficile 630</Bacteria>
    </FastaObject>
    <FastaObject LocusTag="CLOHIR_00687" Name="adhE" Position="-209" Score="5.3">
      <Sequence>ATGATAAAAAAATATCAA</Sequence>
      <Bacteria>Clostridium hiranonis DSM 13275</Bacteria>
    </FastaObject>
    <FastaObject LocusTag="CLOHIR_00139" Name="phf1" Position="-107" Score="4.8">
      <Sequence>ATGTTAAAAATATAAAGA</Sequence>
      <Bacteria>Clostridium hiranonis DSM 13275</Bacteria>
    </FastaObject>
    <FastaObject LocusTag="CLOHIR_00139" Name="phf1" Position="-87" Score="5.1">
      <Sequence>TTGATAAAAAAATGACAA</Sequence>
      <Bacteria>Clostridium hiranonis DSM 13275</Bacteria>
    </FastaObject>
    <FastaObject LocusTag="CLOHIR_00157" Name="nadA" Position="-210" Score="5.5">
      <Sequence>ATGATAAAAAAATAACAA</Sequence>
      <Bacteria>Clostridium hiranonis DSM 13275</Bacteria>
    </FastaObject>
    <FastaObject LocusTag="CLOHIR_00157" Name="nadA" Position="-38" Score="5.4">
      <Sequence>TAGATAAAAAAATAACAA</Sequence>
      <Bacteria>Clostridium hiranonis DSM 13275</Bacteria>
    </FastaObject>
    <FastaObject LocusTag="CLOHIR_00042" Name="rex" Position="-55" Score="4.3">
      <Sequence>ATGTTATATAATAAACCA</Sequence>
      <Bacteria>Clostridium hiranonis DSM 13275</Bacteria>
    </FastaObject>
    <FastaObject LocusTag="CLOHIR_00042" Name="rex" Position="-101" Score="4">
      <Sequence>TTGATATAATATATTCAA</Sequence>
      <Bacteria>Clostridium hiranonis DSM 13275</Bacteria>
    </FastaObject>
  </Sites>
</MotifSite>