<?xml version="1.0" encoding="utf-16"?>
<MotifSite xmlns:xsd="http://www.w3.org/2001/XMLSchema" xmlns:xsi="http://www.w3.org/2001/XMLSchema-instance" logo="http://regprecise.lbl.gov/RegPrecise/logos/4799_large.png">
  <Family>ArgR</Family>
  <RegulationMode>repressor</RegulationMode>
  <BiologicalProcess>Arginine biosynthesis</BiologicalProcess>
  <Effector>Arginine</Effector>
  <Regulog Key="ArgR - Clostridia-1" Value="http://regprecise.lbl.gov/RegPrecise/regulog.jsp?regulog_id=4799" />
  <Taxonomy Key="Clostridia-1" Value="http://regprecise.lbl.gov/RegPrecise/collection_tax.jsp?collection_id=160" />
  <Sites>
    <FastaObject LocusTag="CAC0376" Name="" Position="-65" Score="4.6">
      <Sequence>TCGTATAAATATTAAA</Sequence>
      <Bacteria>Clostridium acetobutylicum ATCC 824</Bacteria>
    </FastaObject>
    <FastaObject LocusTag="CAC0376" Name="" Position="-44" Score="4.6">
      <Sequence>TTGTATACAAATACAA</Sequence>
      <Bacteria>Clostridium acetobutylicum ATCC 824</Bacteria>
    </FastaObject>
    <FastaObject LocusTag="CAC0380" Name="" Position="-188" Score="4.5">
      <Sequence>ATTAATGAATATAAAT</Sequence>
      <Bacteria>Clostridium acetobutylicum ATCC 824</Bacteria>
    </FastaObject>
    <FastaObject LocusTag="CAC0380" Name="" Position="-131" Score="4.6">
      <Sequence>TTGAATAAATATTCGT</Sequence>
      <Bacteria>Clostridium acetobutylicum ATCC 824</Bacteria>
    </FastaObject>
    <FastaObject LocusTag="CAC0380" Name="" Position="-31" Score="4.9">
      <Sequence>ATGAATAAAAATTCAA</Sequence>
      <Bacteria>Clostridium acetobutylicum ATCC 824</Bacteria>
    </FastaObject>
    <FastaObject LocusTag="CAC0973" Name="argG" Position="-123" Score="5.3">
      <Sequence>ATGAATATTTATAAAA</Sequence>
      <Bacteria>Clostridium acetobutylicum ATCC 824</Bacteria>
    </FastaObject>
    <FastaObject LocusTag="CAC0973" Name="argG" Position="-103" Score="4.7">
      <Sequence>TTGCATAATTATAAGA</Sequence>
      <Bacteria>Clostridium acetobutylicum ATCC 824</Bacteria>
    </FastaObject>
    <FastaObject LocusTag="CAC0973" Name="argG" Position="-83" Score="4.6">
      <Sequence>ATTTATAATAATACCA</Sequence>
      <Bacteria>Clostridium acetobutylicum ATCC 824</Bacteria>
    </FastaObject>
    <FastaObject LocusTag="CAC2390" Name="argC" Position="-117" Score="5.2">
      <Sequence>ATGAATAATTATACAC</Sequence>
      <Bacteria>Clostridium acetobutylicum ATCC 824</Bacteria>
    </FastaObject>
    <FastaObject LocusTag="CAC2390" Name="argC" Position="-97" Score="5">
      <Sequence>CTTTATAAATATTCAA</Sequence>
      <Bacteria>Clostridium acetobutylicum ATCC 824</Bacteria>
    </FastaObject>
    <FastaObject LocusTag="CAC2390" Name="argC" Position="-63" Score="5">
      <Sequence>TTGAATAATTATACTT</Sequence>
      <Bacteria>Clostridium acetobutylicum ATCC 824</Bacteria>
    </FastaObject>
    <FastaObject LocusTag="CAC3620" Name="" Position="-195" Score="5.2">
      <Sequence>ATGCATAAATATTAAT</Sequence>
      <Bacteria>Clostridium acetobutylicum ATCC 824</Bacteria>
    </FastaObject>
    <FastaObject LocusTag="CAC3620" Name="" Position="-70" Score="4.9">
      <Sequence>GTTAATAATTATTCAT</Sequence>
      <Bacteria>Clostridium acetobutylicum ATCC 824</Bacteria>
    </FastaObject>
    <FastaObject LocusTag="CAC3020" Name="argJ" Position="-88" Score="5.3">
      <Sequence>ATGCATAAATATAAAT</Sequence>
      <Bacteria>Clostridium acetobutylicum ATCC 824</Bacteria>
    </FastaObject>
    <FastaObject LocusTag="CAC3020" Name="argJ" Position="-68" Score="5.4">
      <Sequence>TTGAATAATTATAAAA</Sequence>
      <Bacteria>Clostridium acetobutylicum ATCC 824</Bacteria>
    </FastaObject>
    <FastaObject LocusTag="CAC2645" Name="carA" Position="-182" Score="5.3">
      <Sequence>ATGCATAAATATAAAT</Sequence>
      <Bacteria>Clostridium acetobutylicum ATCC 824</Bacteria>
    </FastaObject>
    <FastaObject LocusTag="CAC2645" Name="carA" Position="-81" Score="5.4">
      <Sequence>ATGTATAAATATAAAA</Sequence>
      <Bacteria>Clostridium acetobutylicum ATCC 824</Bacteria>
    </FastaObject>
    <FastaObject LocusTag="CAC2389" Name="argB" Position="-98" Score="5">
      <Sequence>AAGTATAATTATTCAA</Sequence>
      <Bacteria>Clostridium acetobutylicum ATCC 824</Bacteria>
    </FastaObject>
    <FastaObject LocusTag="CAC2389" Name="argB" Position="-64" Score="5">
      <Sequence>TTGAATATTTATAAAG</Sequence>
      <Bacteria>Clostridium acetobutylicum ATCC 824</Bacteria>
    </FastaObject>
    <FastaObject LocusTag="CAC2389" Name="argB" Position="-44" Score="5.2">
      <Sequence>GTGTATAATTATTCAT</Sequence>
      <Bacteria>Clostridium acetobutylicum ATCC 824</Bacteria>
    </FastaObject>
    <FastaObject LocusTag="Cbei_4515" Name="argG" Position="-165" Score="4.7">
      <Sequence>ATGAATATTTTTTCAT</Sequence>
      <Bacteria>Clostridium beijerincki NCIMB 8052</Bacteria>
    </FastaObject>
    <FastaObject LocusTag="Cbei_4515" Name="argG" Position="-122" Score="4.8">
      <Sequence>CTGTATAATTATAAAC</Sequence>
      <Bacteria>Clostridium beijerincki NCIMB 8052</Bacteria>
    </FastaObject>
    <FastaObject LocusTag="Cbei_4515" Name="argG" Position="-46" Score="4.8">
      <Sequence>ATGTATGTTTATGCAT</Sequence>
      <Bacteria>Clostridium beijerincki NCIMB 8052</Bacteria>
    </FastaObject>
    <FastaObject LocusTag="Cbei_4781" Name="artP" Position="-240" Score="4.7">
      <Sequence>TTTTATAATTTTAAAA</Sequence>
      <Bacteria>Clostridium beijerincki NCIMB 8052</Bacteria>
    </FastaObject>
    <FastaObject LocusTag="Cbei_4781" Name="artP" Position="-104" Score="4.9">
      <Sequence>ATGAATAATAATTAAA</Sequence>
      <Bacteria>Clostridium beijerincki NCIMB 8052</Bacteria>
    </FastaObject>
    <FastaObject LocusTag="Cbei_4781" Name="artP" Position="-70" Score="4.6">
      <Sequence>TTGAGTAAATATAAAA</Sequence>
      <Bacteria>Clostridium beijerincki NCIMB 8052</Bacteria>
    </FastaObject>
    <FastaObject LocusTag="Cbei_4781" Name="artP" Position="-50" Score="4.6">
      <Sequence>GTGTATAATTATGCTA</Sequence>
      <Bacteria>Clostridium beijerincki NCIMB 8052</Bacteria>
    </FastaObject>
    <FastaObject LocusTag="CBO2670" Name="argG" Position="-256" Score="4.7">
      <Sequence>GTGCATAATTATAAAG</Sequence>
      <Bacteria>Clostridium botulinum A str. ATCC 3502</Bacteria>
    </FastaObject>
    <FastaObject LocusTag="CBO2670" Name="argG" Position="-139" Score="4.6">
      <Sequence>TTGCATATTTATTATT</Sequence>
      <Bacteria>Clostridium botulinum A str. ATCC 3502</Bacteria>
    </FastaObject>
    <FastaObject LocusTag="CBO2670" Name="argG" Position="-119" Score="5.6">
      <Sequence>ATGTATAATTATAAAA</Sequence>
      <Bacteria>Clostridium botulinum A str. ATCC 3502</Bacteria>
    </FastaObject>
    <FastaObject LocusTag="CBO1788" Name="argT" Position="-62" Score="5.4">
      <Sequence>TTTTATATTTATACAT</Sequence>
      <Bacteria>Clostridium botulinum A str. ATCC 3502</Bacteria>
    </FastaObject>
    <FastaObject LocusTag="CBO2018" Name="artP" Position="-43" Score="5.2">
      <Sequence>ATGCATAATTATACAG</Sequence>
      <Bacteria>Clostridium botulinum A str. ATCC 3502</Bacteria>
    </FastaObject>
    <FastaObject LocusTag="CBY_1679" Name="argG" Position="-87" Score="5.6">
      <Sequence>ATGTATAATTATAAAA</Sequence>
      <Bacteria>Clostridium butyricum 5521</Bacteria>
    </FastaObject>
    <FastaObject LocusTag="CBY_2294" Name="argT" Position="-31" Score="5.1">
      <Sequence>TTGTATATTTATAAAG</Sequence>
      <Bacteria>Clostridium butyricum 5521</Bacteria>
    </FastaObject>
    <FastaObject LocusTag="CBY_2294" Name="argT" Position="0" Score="5.1">
      <Sequence>ATGAATAATAATTCAA</Sequence>
      <Bacteria>Clostridium butyricum 5521</Bacteria>
    </FastaObject>
    <FastaObject LocusTag="CBY_1781" Name="artP" Position="-110" Score="4.7">
      <Sequence>TTTAATATTTATTTAT</Sequence>
      <Bacteria>Clostridium butyricum 5521</Bacteria>
    </FastaObject>
    <FastaObject LocusTag="CBY_1781" Name="artP" Position="-76" Score="5.4">
      <Sequence>TTGAATAATTATAAAA</Sequence>
      <Bacteria>Clostridium butyricum 5521</Bacteria>
    </FastaObject>
    <FastaObject LocusTag="CBY_1781" Name="artP" Position="-56" Score="5.2">
      <Sequence>ATGTATAATTATACTA</Sequence>
      <Bacteria>Clostridium butyricum 5521</Bacteria>
    </FastaObject>
    <FastaObject LocusTag="CKL_1553" Name="argC" Position="-257" Score="4.7">
      <Sequence>TTGTACATTTATAAAA</Sequence>
      <Bacteria>Clostridium kluyveri DSM 555</Bacteria>
    </FastaObject>
    <FastaObject LocusTag="CKL_1553" Name="argC" Position="-224" Score="4.6">
      <Sequence>TTGTATATTTATAATG</Sequence>
      <Bacteria>Clostridium kluyveri DSM 555</Bacteria>
    </FastaObject>
    <FastaObject LocusTag="CKL_1553" Name="argC" Position="-123" Score="4.8">
      <Sequence>ATTAATTTTTATAAAA</Sequence>
      <Bacteria>Clostridium kluyveri DSM 555</Bacteria>
    </FastaObject>
    <FastaObject LocusTag="CKL_1553" Name="argC" Position="-102" Score="4.8">
      <Sequence>TTGCATATTTATTTAT</Sequence>
      <Bacteria>Clostridium kluyveri DSM 555</Bacteria>
    </FastaObject>
    <FastaObject LocusTag="CKL_2377" Name="artP2" Position="-222" Score="4.9">
      <Sequence>ATGTATATGTATAAAT</Sequence>
      <Bacteria>Clostridium kluyveri DSM 555</Bacteria>
    </FastaObject>
    <FastaObject LocusTag="CKL_2377" Name="artP2" Position="-122" Score="4.6">
      <Sequence>ATGTATAATTATAAGG</Sequence>
      <Bacteria>Clostridium kluyveri DSM 555</Bacteria>
    </FastaObject>
    <FastaObject LocusTag="CKL_0978" Name="artP2" Position="-88" Score="4.8">
      <Sequence>TTGCATAATTATAATA</Sequence>
      <Bacteria>Clostridium kluyveri DSM 555</Bacteria>
    </FastaObject>
    <FastaObject LocusTag="CKL_0978" Name="artP2" Position="-68" Score="5.1">
      <Sequence>ATGTATAATTATTTAT</Sequence>
      <Bacteria>Clostridium kluyveri DSM 555</Bacteria>
    </FastaObject>
    <FastaObject LocusTag="NT01CX_0138" Name="artP2" Position="-254" Score="5.1">
      <Sequence>ATATATAATTATAAAA</Sequence>
      <Bacteria>Clostridium novyi NT</Bacteria>
    </FastaObject>
    <FastaObject LocusTag="NT01CX_0138" Name="artP2" Position="-232" Score="4.5">
      <Sequence>ATGTATAATAATACTG</Sequence>
      <Bacteria>Clostridium novyi NT</Bacteria>
    </FastaObject>
    <FastaObject LocusTag="NT01CX_0138" Name="artP2" Position="-158" Score="4.8">
      <Sequence>TTGTATATGTATAAAA</Sequence>
      <Bacteria>Clostridium novyi NT</Bacteria>
    </FastaObject>
    <FastaObject LocusTag="NT01CX_0138" Name="artP2" Position="-138" Score="5.3">
      <Sequence>TTGAATAAATATTCAT</Sequence>
      <Bacteria>Clostridium novyi NT</Bacteria>
    </FastaObject>
    <FastaObject LocusTag="NT01CX_0138" Name="artP2" Position="-115" Score="4.8">
      <Sequence>TTGCATAATTATAATA</Sequence>
      <Bacteria>Clostridium novyi NT</Bacteria>
    </FastaObject>
    <FastaObject LocusTag="NT01CX_0138" Name="artP2" Position="-95" Score="5.1">
      <Sequence>ATGTATAATTATTTAT</Sequence>
      <Bacteria>Clostridium novyi NT</Bacteria>
    </FastaObject>
    <FastaObject LocusTag="NT01CX_0138" Name="artP2" Position="-10" Score="4.9">
      <Sequence>GTGTATAAATATGAAA</Sequence>
      <Bacteria>Clostridium novyi NT</Bacteria>
    </FastaObject>
    <FastaObject LocusTag="NT01CX_2379" Name="argC" Position="-132" Score="5">
      <Sequence>TTGAATAATTATACTA</Sequence>
      <Bacteria>Clostridium novyi NT</Bacteria>
    </FastaObject>
    <FastaObject LocusTag="NT01CX_2379" Name="argC" Position="-59" Score="4.9">
      <Sequence>TTGAATAATTATGCTT</Sequence>
      <Bacteria>Clostridium novyi NT</Bacteria>
    </FastaObject>
    <FastaObject LocusTag="NT01CX_1828" Name="argT" Position="-92" Score="5.2">
      <Sequence>TTGTATTATTATAAAT</Sequence>
      <Bacteria>Clostridium novyi NT</Bacteria>
    </FastaObject>
    <FastaObject LocusTag="NT01CX_1828" Name="argT" Position="-72" Score="5.3">
      <Sequence>ATGCATAAATATAAAA</Sequence>
      <Bacteria>Clostridium novyi NT</Bacteria>
    </FastaObject>
    <FastaObject LocusTag="NT01CX_0932" Name="artP" Position="-267" Score="4.6">
      <Sequence>TTTTAAAAATATGCAA</Sequence>
      <Bacteria>Clostridium novyi NT</Bacteria>
    </FastaObject>
    <FastaObject LocusTag="NT01CX_0932" Name="artP" Position="-115" Score="5">
      <Sequence>GTGTATAAATATAAAT</Sequence>
      <Bacteria>Clostridium novyi NT</Bacteria>
    </FastaObject>
    <FastaObject LocusTag="NT01CX_0932" Name="artP" Position="-84" Score="4.8">
      <Sequence>ATACATAAATATTCAT</Sequence>
      <Bacteria>Clostridium novyi NT</Bacteria>
    </FastaObject>
    <FastaObject LocusTag="NT01CX_0932" Name="artP" Position="-61" Score="5.4">
      <Sequence>TTGCATAATTATAAAT</Sequence>
      <Bacteria>Clostridium novyi NT</Bacteria>
    </FastaObject>
    <FastaObject LocusTag="NT01CX_0383" Name="carA" Position="-77" Score="5.3">
      <Sequence>ATGTATAAATATGAAA</Sequence>
      <Bacteria>Clostridium novyi NT</Bacteria>
    </FastaObject>
    <FastaObject LocusTag="NT01CX_0383" Name="carA" Position="-57" Score="5.1">
      <Sequence>ATGTATAAAAATTCAA</Sequence>
      <Bacteria>Clostridium novyi NT</Bacteria>
    </FastaObject>
    <FastaObject LocusTag="NT01CX_2380" Name="argB" Position="-102" Score="4.9">
      <Sequence>AAGCATAATTATTCAA</Sequence>
      <Bacteria>Clostridium novyi NT</Bacteria>
    </FastaObject>
    <FastaObject LocusTag="NT01CX_2380" Name="argB" Position="-29" Score="5">
      <Sequence>TAGTATAATTATTCAA</Sequence>
      <Bacteria>Clostridium novyi NT</Bacteria>
    </FastaObject>
    <FastaObject LocusTag="CPF_0683" Name="argG" Position="-72" Score="4.9">
      <Sequence>TTGCATAAATATACTT</Sequence>
      <Bacteria>Clostridium perfringens ATCC 13124</Bacteria>
    </FastaObject>
    <FastaObject LocusTag="CPF_0683" Name="argG" Position="-52" Score="5">
      <Sequence>ATGTATAATTATTAAC</Sequence>
      <Bacteria>Clostridium perfringens ATCC 13124</Bacteria>
    </FastaObject>
    <FastaObject LocusTag="CPF_2910" Name="argT" Position="-117" Score="5.4">
      <Sequence>TTGAATATTTATACAT</Sequence>
      <Bacteria>Clostridium perfringens ATCC 13124</Bacteria>
    </FastaObject>
    <FastaObject LocusTag="CPF_0581" Name="artP" Position="-261" Score="4.6">
      <Sequence>ATGTATAAAAACACAA</Sequence>
      <Bacteria>Clostridium perfringens ATCC 13124</Bacteria>
    </FastaObject>
    <FastaObject LocusTag="CPF_0581" Name="artP" Position="-77" Score="4.9">
      <Sequence>TTGCATTTTTATTCAT</Sequence>
      <Bacteria>Clostridium perfringens ATCC 13124</Bacteria>
    </FastaObject>
    <FastaObject LocusTag="CPF_0581" Name="artP" Position="-56" Score="5.6">
      <Sequence>ATGTATAATTATTCAA</Sequence>
      <Bacteria>Clostridium perfringens ATCC 13124</Bacteria>
    </FastaObject>
    <FastaObject LocusTag="CTC00557" Name="artP2" Position="-226" Score="4.8">
      <Sequence>ATGTATAAATATTCGA</Sequence>
      <Bacteria>Clostridium tetani E88</Bacteria>
    </FastaObject>
    <FastaObject LocusTag="CTC00557" Name="artP2" Position="-73" Score="5.3">
      <Sequence>TTGCATAAATATAAAT</Sequence>
      <Bacteria>Clostridium tetani E88</Bacteria>
    </FastaObject>
    <FastaObject LocusTag="CTC00841" Name="argT" Position="-64" Score="4.7">
      <Sequence>ATTAATATTTATGCAC</Sequence>
      <Bacteria>Clostridium tetani E88</Bacteria>
    </FastaObject>
    <FastaObject LocusTag="CTC00841" Name="argT" Position="-34" Score="5.1">
      <Sequence>TTGCATAAATATTAAT</Sequence>
      <Bacteria>Clostridium tetani E88</Bacteria>
    </FastaObject>
  </Sites>
</MotifSite>