<?xml version="1.0" encoding="utf-16"?>
<MotifSite xmlns:xsd="http://www.w3.org/2001/XMLSchema" xmlns:xsi="http://www.w3.org/2001/XMLSchema-instance" logo="http://regprecise.lbl.gov/RegPrecise/logos/6218_large.png">
  <Family>GntR/MocR</Family>
  <RegulationMode />
  <BiologicalProcess>Metabolite transport</BiologicalProcess>
  <Effector />
  <Regulog Key="CPS_4612 - Alteromonadales" Value="http://regprecise.lbl.gov/RegPrecise/regulog.jsp?regulog_id=6218" />
  <Taxonomy Key="Alteromonadales" Value="http://regprecise.lbl.gov/RegPrecise/collection_tax.jsp?collection_id=107" />
  <Sites>
    <FastaObject LocusTag="CPS_4613" Name="PF00892" Position="-370" Score="8.4">
      <Sequence>AACTGTATAGG--------------TTTTGTATATG</Sequence>
      <Bacteria>Colwellia psychrerythraea 34H</Bacteria>
    </FastaObject>
    <FastaObject LocusTag="PTD2_06135" Name="PF00892" Position="-96" Score="9.7">
      <Sequence>ATCTGTATAGG--------------ATCTGTATATG</Sequence>
      <Bacteria>Pseudoalteromonas tunicata D2</Bacteria>
    </FastaObject>
    <FastaObject LocusTag="PSHAa0058" Name="PF00892" Position="-91" Score="9.4">
      <Sequence>ATCTGTATAGG--------------TTCTGTATATG</Sequence>
      <Bacteria>Pseudoalteromonas haloplanktis TAC125</Bacteria>
    </FastaObject>
  </Sites>
</MotifSite>