<?xml version="1.0" encoding="utf-16"?>
<MotifSite xmlns:xsd="http://www.w3.org/2001/XMLSchema" xmlns:xsi="http://www.w3.org/2001/XMLSchema-instance" logo="http://regprecise.lbl.gov/RegPrecise/logos/5037_large.png">
  <Family>HrcA</Family>
  <RegulationMode>repressor</RegulationMode>
  <BiologicalProcess>Heat shock response</BiologicalProcess>
  <Effector>Heat shock</Effector>
  <Regulog Key="HrcA - Rhodobacterales" Value="http://regprecise.lbl.gov/RegPrecise/regulog.jsp?regulog_id=5037" />
  <Taxonomy Key="Rhodobacterales" Value="http://regprecise.lbl.gov/RegPrecise/collection_tax.jsp?collection_id=118" />
  <Sites>
    <FastaObject LocusTag="RSP_2310" Name="groS" Position="-62" Score="7.5">
      <Sequence>TTGGCACTCGCCTCGGGTGAGTGCTAA</Sequence>
      <Bacteria>Rhodobacter sphaeroides 2.4.1</Bacteria>
    </FastaObject>
    <FastaObject LocusTag="Pden_3654" Name="groL" Position="-396" Score="7.2">
      <Sequence>TTGGCACTCACCCGAGCCGAGTGCCAA</Sequence>
      <Bacteria>Paracoccus denitrificans PD1222</Bacteria>
    </FastaObject>
    <FastaObject LocusTag="Jann_3359" Name="groS" Position="-72" Score="6.9">
      <Sequence>TTGGCACTCGCGTTCGGTGAGTGCTAA</Sequence>
      <Bacteria>Jannaschia sp. CCS1</Bacteria>
    </FastaObject>
    <FastaObject LocusTag="RB2654_08122" Name="groS" Position="-86" Score="7.4">
      <Sequence>TTAGCACTCACCCCCGGTGAGTGCCAA</Sequence>
      <Bacteria>Rhodobacterales bacterium HTCC2654</Bacteria>
    </FastaObject>
    <FastaObject LocusTag="OG2516_17151" Name="groS" Position="-54" Score="7.5">
      <Sequence>TTAGCACTCACACCGAGCGAGTGCTAA</Sequence>
      <Bacteria>Oceanicola granulosus HTCC2516</Bacteria>
    </FastaObject>
    <FastaObject LocusTag="SKA53_08661" Name="groS" Position="-60" Score="7.1">
      <Sequence>TTGGCACTCGGACTGGCTGAGTGCTAA</Sequence>
      <Bacteria>Loktanella vestfoldensis SKA53</Bacteria>
    </FastaObject>
    <FastaObject LocusTag="OB2597_07485" Name="groS" Position="-94" Score="7.1">
      <Sequence>TTAGCACTCGCGTGGTGTGAGTGATAA</Sequence>
      <Bacteria>Oceanicola batsensis HTCC2597</Bacteria>
    </FastaObject>
    <FastaObject LocusTag="ISM_05760" Name="groS" Position="-79" Score="7.2">
      <Sequence>TTAGCACTCGGAGGGACTGAGTGCTAA</Sequence>
      <Bacteria>Roseovarius nubinhibens ISM</Bacteria>
    </FastaObject>
    <FastaObject LocusTag="ROS217_12501" Name="groS" Position="-81" Score="7">
      <Sequence>TTAGCACTCGAACCCCATGAGTGCTAA</Sequence>
      <Bacteria>Roseovarius sp. 217</Bacteria>
    </FastaObject>
    <FastaObject LocusTag="EE36_03888" Name="groS" Position="-92" Score="7.6">
      <Sequence>TTAGCACTCGGCAGGGCTGAGTGCTAA</Sequence>
      <Bacteria>Sulfitobacter sp. EE-36</Bacteria>
    </FastaObject>
    <FastaObject LocusTag="TM1040_0596" Name="groS" Position="-94" Score="7.5">
      <Sequence>TTAGCACTCGACTGAGGTGAGTGCTAA</Sequence>
      <Bacteria>Silicibacter TM1040</Bacteria>
    </FastaObject>
    <FastaObject LocusTag="SPO0886" Name="groS" Position="-86" Score="7.2">
      <Sequence>TTAGCACTCGTCAGACCTGAGTGCTAA</Sequence>
      <Bacteria>Silicibacter pomeroyi DSS-3</Bacteria>
    </FastaObject>
    <FastaObject LocusTag="MED193_20209" Name="groS" Position="-93" Score="7.1">
      <Sequence>TTAGCACTCATCAGGTGTGAGTGATAA</Sequence>
      <Bacteria>Roseobacter sp. MED193</Bacteria>
    </FastaObject>
    <FastaObject LocusTag="HNE_1961" Name="groS" Position="-110" Score="7.4">
      <Sequence>TTAGCAGTCGGCTCGGGCGAGTGCTAA</Sequence>
      <Bacteria>Hyphomonas neptunium ATCC 15444</Bacteria>
    </FastaObject>
    <FastaObject LocusTag="OA2633_05922" Name="groS" Position="-94" Score="6.4">
      <Sequence>TTAGCAGCCAGGGCAGGAGAGTGCTAA</Sequence>
      <Bacteria>Oceanicaulis alexandrii HTCC2633</Bacteria>
    </FastaObject>
  </Sites>
</MotifSite>