<?xml version="1.0" encoding="utf-16"?>
<MotifSite xmlns:xsd="http://www.w3.org/2001/XMLSchema" xmlns:xsi="http://www.w3.org/2001/XMLSchema-instance" logo="http://regprecise.lbl.gov/RegPrecise/logos/3968_large.png">
  <Family>TetR</Family>
  <RegulationMode>repressor</RegulationMode>
  <BiologicalProcess>Phenylacetic acid degradation</BiologicalProcess>
  <Effector>Phenylacetyl-CoA</Effector>
  <Regulog Key="PaaR - Burkholderia" Value="http://regprecise.lbl.gov/RegPrecise/regulog.jsp?regulog_id=3968" />
  <Taxonomy Key="Burkholderia" Value="http://regprecise.lbl.gov/RegPrecise/collection_tax.jsp?collection_id=114" />
  <Sites>
    <FastaObject LocusTag="BPSL3041" Name="paaZ" Position="-64" Score="6.4">
      <Sequence>TCCGACCAACCGGTCGGTTAAT</Sequence>
      <Bacteria>Burkholderia pseudomallei K96243</Bacteria>
    </FastaObject>
    <FastaObject LocusTag="BPSL3230" Name="paaA" Position="-62" Score="7.1">
      <Sequence>ATTAACCGACCGGTCGGTTGGT</Sequence>
      <Bacteria>Burkholderia pseudomallei K96243</Bacteria>
    </FastaObject>
    <FastaObject LocusTag="BPSL3040" Name="paaG" Position="-70" Score="6.6">
      <Sequence>ATTAACCGACCGGTTGGTCGGA</Sequence>
      <Bacteria>Burkholderia pseudomallei K96243</Bacteria>
    </FastaObject>
    <FastaObject LocusTag="BMA2573" Name="paaA" Position="-62" Score="7.1">
      <Sequence>ATTAACCGACCGGTCGGTTGGT</Sequence>
      <Bacteria>Burkholderia mallei ATCC 23344</Bacteria>
    </FastaObject>
    <FastaObject LocusTag="BMAA0543" Name="paaZ" Position="-64" Score="6">
      <Sequence>TCCGACTAACCGGTCGGTTAAT</Sequence>
      <Bacteria>Burkholderia mallei ATCC 23344</Bacteria>
    </FastaObject>
    <FastaObject LocusTag="BMAA0544" Name="paaG" Position="-88" Score="6.1">
      <Sequence>ATTAACCGACCGGTTAGTCGGA</Sequence>
      <Bacteria>Burkholderia mallei ATCC 23344</Bacteria>
    </FastaObject>
    <FastaObject LocusTag="Bcep18194_A3630" Name="paaZ" Position="-63" Score="6.4">
      <Sequence>TCCGACCAACCGGTCGGTTAAT</Sequence>
      <Bacteria>Burkholderia sp. 383</Bacteria>
    </FastaObject>
    <FastaObject LocusTag="Bcep18194_B1317" Name="paaH" Position="-60" Score="6.3">
      <Sequence>ATATACCGACCGGTCGGTTTAT</Sequence>
      <Bacteria>Burkholderia sp. 383</Bacteria>
    </FastaObject>
    <FastaObject LocusTag="Bcep18194_A3429" Name="paaA" Position="-61" Score="7.1">
      <Sequence>ATTAACCGACCGGTCGGTTGGT</Sequence>
      <Bacteria>Burkholderia sp. 383</Bacteria>
    </FastaObject>
    <FastaObject LocusTag="Bcep18194_A3631" Name="paaG" Position="-88" Score="6.6">
      <Sequence>ATTAACCGACCGGTTGGTCGGA</Sequence>
      <Bacteria>Burkholderia sp. 383</Bacteria>
    </FastaObject>
    <FastaObject LocusTag="Bamb_0448" Name="paaZ" Position="-63" Score="6.4">
      <Sequence>TCCGACCAACCGGTCGGTTAAT</Sequence>
      <Bacteria>Burkholderia cepacia AMMD</Bacteria>
    </FastaObject>
    <FastaObject LocusTag="Bamb_0449" Name="paaG" Position="-88" Score="6.6">
      <Sequence>ATTAACCGACCGGTTGGTCGGA</Sequence>
      <Bacteria>Burkholderia cepacia AMMD</Bacteria>
    </FastaObject>
    <FastaObject LocusTag="Bamb_3960" Name="paaH" Position="-61" Score="6.6">
      <Sequence>ATCTACCGACCGGTCGGTTTAT</Sequence>
      <Bacteria>Burkholderia cepacia AMMD</Bacteria>
    </FastaObject>
    <FastaObject LocusTag="Bamb_0249" Name="paaA" Position="-62" Score="7.1">
      <Sequence>ATTAACCGACCGGTCGGTTGGT</Sequence>
      <Bacteria>Burkholderia cepacia AMMD</Bacteria>
    </FastaObject>
    <FastaObject LocusTag="bglu_1g02410" Name="paaA" Position="-62" Score="6.8">
      <Sequence>ATTAACCGACCGGACGGTTGGT</Sequence>
      <Bacteria>Burkholderia glumae BGR1</Bacteria>
    </FastaObject>
    <FastaObject LocusTag="bglu_1g04490" Name="paaZ" Position="-70" Score="6.2">
      <Sequence>GCCGACCAACCGGTCGGTTAAT</Sequence>
      <Bacteria>Burkholderia glumae BGR1</Bacteria>
    </FastaObject>
    <FastaObject LocusTag="bglu_1g04500" Name="paaG" Position="-87" Score="6.5">
      <Sequence>ATTAACCGACCGGTTGGTCGGC</Sequence>
      <Bacteria>Burkholderia glumae BGR1</Bacteria>
    </FastaObject>
    <FastaObject LocusTag="Bcep1808_0520" Name="paaZ" Position="-63" Score="6.4">
      <Sequence>TCCGACCAACCGGTCGGTTAAT</Sequence>
      <Bacteria>Burkholderia vietnamiensis G4</Bacteria>
    </FastaObject>
    <FastaObject LocusTag="Bcep1808_5069" Name="paaH" Position="-61" Score="6.6">
      <Sequence>ATCTACCGACCGGTCGGTTTAT</Sequence>
      <Bacteria>Burkholderia vietnamiensis G4</Bacteria>
    </FastaObject>
    <FastaObject LocusTag="Bcep1808_0521" Name="paaG" Position="-88" Score="6.6">
      <Sequence>ATTAACCGACCGGTTGGTCGGA</Sequence>
      <Bacteria>Burkholderia vietnamiensis G4</Bacteria>
    </FastaObject>
    <FastaObject LocusTag="Bcep1808_0312" Name="paaA" Position="-62" Score="7.1">
      <Sequence>ATTAACCGACCGGTCGGTTGGT</Sequence>
      <Bacteria>Burkholderia vietnamiensis G4</Bacteria>
    </FastaObject>
    <FastaObject LocusTag="Bxe_A0470" Name="paaZ" Position="-66" Score="6.2">
      <Sequence>CCCAACCAACCGGTCGGTCAAT</Sequence>
      <Bacteria>Burkholderia xenovorans LB400</Bacteria>
    </FastaObject>
    <FastaObject LocusTag="Bxe_A0471" Name="paaG" Position="-93" Score="6.5">
      <Sequence>ATTGACCGACCGGTTGGTTGGG</Sequence>
      <Bacteria>Burkholderia xenovorans LB400</Bacteria>
    </FastaObject>
    <FastaObject LocusTag="Bxe_A0295" Name="paaA" Position="-65" Score="7.1">
      <Sequence>ATTAACCGACCGGTCGGTTGGT</Sequence>
      <Bacteria>Burkholderia xenovorans LB400</Bacteria>
    </FastaObject>
    <FastaObject LocusTag="Bphy_2689" Name="paaZ" Position="-68" Score="6.6">
      <Sequence>ACCAACCAACCGGTCGGTCAAT</Sequence>
      <Bacteria>Burkholderia phymatum STM815</Bacteria>
    </FastaObject>
    <FastaObject LocusTag="Bphy_2688" Name="paaG" Position="-90" Score="6.9">
      <Sequence>ATTGACCGACCGGTTGGTTGGT</Sequence>
      <Bacteria>Burkholderia phymatum STM815</Bacteria>
    </FastaObject>
    <FastaObject LocusTag="Bphy_2857" Name="paaA" Position="-66" Score="6.8">
      <Sequence>ATTAACCGACCGGACGGTTGGT</Sequence>
      <Bacteria>Burkholderia phymatum STM815</Bacteria>
    </FastaObject>
  </Sites>
</MotifSite>